devscholar_jupyter/__init__.py
devscholar_jupyter/_version.py
devscholar_jupyter-0.2.0.data/data/share/jupyter/labextensions/devscholar-jupyter/package.json
devscholar_jupyter-0.2.0.data/data/share/jupyter/labextensions/devscholar-jupyter/schemas/devscholar-jupyter/package.json.orig
devscholar_jupyter-0.2.0.data/data/share/jupyter/labextensions/devscholar-jupyter/schemas/devscholar-jupyter/plugin.json
devscholar_jupyter-0.2.0.data/data/share/jupyter/labextensions/devscholar-jupyter/static/181.b1619da5fa28204279a1.js
devscholar_jupyter-0.2.0.data/data/share/jupyter/labextensions/devscholar-jupyter/static/206.4b33855c4f6d6bce384e.js
devscholar_jupyter-0.2.0.data/data/share/jupyter/labextensions/devscholar-jupyter/static/remoteEntry.7be6601810ca23107d91.js
devscholar_jupyter-0.2.0.data/data/share/jupyter/labextensions/devscholar-jupyter/static/style.js
devscholar_jupyter-0.2.0.data/data/share/jupyter/labextensions/devscholar-jupyter/static/third-party-licenses.json
devscholar_jupyter-0.2.0.data/data/share/jupyter/labextensions/devscholar-jupyter/install.json
devscholar_jupyter-0.2.0.dist-info/METADATA
devscholar_jupyter-0.2.0.dist-info/WHEEL
devscholar_jupyter-0.2.0.dist-info/licenses/LICENSE
devscholar_jupyter-0.2.0.dist-info/RECORD
