Metadata-Version: 2.4
Name: devscholar_jupyter
Version: 0.2.0
Summary: DevScholar for JupyterLab - Link research papers (arXiv, DOI, IEEE) directly in your notebooks with hover metadata and PDF preview
Project-URL: Homepage, https://github.com/pallaprolus/devscholar-jupyter
Project-URL: Bug Tracker, https://github.com/pallaprolus/devscholar-jupyter/issues
Project-URL: Repository, https://github.com/pallaprolus/devscholar-jupyter.git
Author-email: Sudhakar Pallaprolu <pallaprolus@gmail.com>
License: MIT License
License-File: LICENSE
Keywords: academic,arxiv,bibliography,citations,jupyter,jupyterlab,jupyterlab-extension,research
Classifier: Framework :: Jupyter
Classifier: Framework :: Jupyter :: JupyterLab
Classifier: Framework :: Jupyter :: JupyterLab :: 4
Classifier: Framework :: Jupyter :: JupyterLab :: Extensions
Classifier: Framework :: Jupyter :: JupyterLab :: Extensions :: Prebuilt
Classifier: License :: OSI Approved :: MIT License
Classifier: Programming Language :: Python
Classifier: Programming Language :: Python :: 3
Classifier: Programming Language :: Python :: 3.8
Classifier: Programming Language :: Python :: 3.9
Classifier: Programming Language :: Python :: 3.10
Classifier: Programming Language :: Python :: 3.11
Classifier: Programming Language :: Python :: 3.12
Requires-Python: >=3.8
